masscan/__init__.py
masscan/example.py
masscan/masscan.py
python_masscan-0.1.3.dist-info/METADATA
python_masscan-0.1.3.dist-info/RECORD
python_masscan-0.1.3.dist-info/WHEEL
python_masscan-0.1.3.dist-info/top_level.txt
